tennis_big3/__init__.py
tennis_big3/players.py
tennis_big3/utils.py
tennis_big3-0.1.2.dist-info/METADATA
tennis_big3-0.1.2.dist-info/WHEEL
tennis_big3-0.1.2.dist-info/top_level.txt
tennis_big3-0.1.2.dist-info/RECORD
