Metadata-Version: 2.1
Name: tennis-big3
Version: 0.1.2
Summary: Library which shows stats about the Big Three era in Tennis (2000's, 2010's)
Home-page: https://es.wikipedia.org/wiki/Big_Three_(tenis)
Author: Javier Gutiérrez
